glyFacialDetection/DetectedArea.py
glyFacialDetection/FrameThread.py
glyFacialDetection/GlyLibrary.py
glyFacialDetection/HelperFunctions.py
glyFacialDetection/ImageManager.py
glyFacialDetection/Point.py
glyFacialDetection/ServerVideoManager.py
glyFacialDetection/VideoManager.py
glyFacialDetection/__init__.py
glyFacialDetection-0.0.18.dist-info/LICENSE.txt
glyFacialDetection-0.0.18.dist-info/METADATA
glyFacialDetection-0.0.18.dist-info/WHEEL
glyFacialDetection-0.0.18.dist-info/top_level.txt
glyFacialDetection-0.0.18.dist-info/RECORD
